{
  "tags" : [ {
    "description" : "Rest service swagger documentation",
    "name" : "RestServiceVirtualController"
  } ],
  "basePath" : "${rest.GetCountOfDepts.basepath}",
  "paths" : {
    "/TESTINGAPI_S/services/hrdb/Department/count" : {
      "x-WM-BASE_PATH" : "/TESTINGAPI_S/services/hrdb/Department/count",
      "x-WM-TAG" : "RestServiceVirtualController",
      "get" : {
        "tags" : [ "RestServiceVirtualController" ],
        "x-WM-METHOD_NAME" : "invoke",
        "x-WM-ACCESS_SPECIFIER" : "APP_ONLY",
        "produces" : [ "application/json" ],
        "consumes" : [ "text/xml" ],
        "responses" : {
          "200" : {
            "schema" : {
              "$ref" : "#/definitions/RootResponse"
            },
            "description" : "Success"
          }
        },
        "operationId" : "GetCountOfDepts_RestServiceVirtualController-invoke"
      },
      "x-WM-RELATIVE_PATH" : "",
      "x-WM-COMPLETE_PATH" : "${rest.GetCountOfDepts.scheme}://${rest.GetCountOfDepts.host}${rest.GetCountOfDepts.basepath}/TESTINGAPI_S/services/hrdb/Department/count"
    }
  },
  "host" : "${rest.GetCountOfDepts.host}",
  "schemes" : [ "${rest.GetCountOfDepts.scheme}" ],
  "swagger" : "2.0",
  "definitions" : {
    "RootResponse" : {
      "x-WM-FULLY_QUALIFIED_NAME" : "GetCountOfDepts.RootResponse",
      "x-WM-TAGS" : [ "RestServiceVirtualController" ]
    }
  },
  "info" : {
    "x-WM-SERVICE_TYPE" : "RestService",
    "x-WM-API_ID" : "fb2465c4-e412-4e89-8e47-fc994cde37a9",
    "x-WM-USE_PROXY_FOR_WEB" : true,
    "x-WM-SERVICE_ID" : "wavemakeronline",
    "x-WM-USE_PROXY_FOR_MOBILE" : true,
    "version" : "2.0"
  }
}